setup.py
csvtodict/__init__.py
csvtodict/csvtodict.py
csvtodict.egg-info/PKG-INFO
csvtodict.egg-info/SOURCES.txt
csvtodict.egg-info/dependency_links.txt
csvtodict.egg-info/not-zip-safe
csvtodict.egg-info/top_level.txt