Metadata-Version: 1.0
Name: csvtodict
Version: 0.1
Summary: Converts spreadsheets to python OrderedDictionaries
Home-page: https://github.com/cmw228/csvtodict
Author: Chris Wacker
Author-email: chriswacker228@gmail.com
License: MIT
Platform: UNKNOWN
